prodapi/__init__.py
prodapi/applications.py
prodapi/info.py
prodapi/models/__init__.py
prodapi/models/misc.py
prodapi/routes/__init__.py
prodapi/routes/health.py
prodapi/routes/user.py
prodapi/sec.py
prodapi-0.1.0.dist-info/LICENSE
prodapi-0.1.0.dist-info/WHEEL
prodapi-0.1.0.dist-info/METADATA
prodapi-0.1.0.dist-info/RECORD
