Metadata-Version: 2.1
Name: prodapi
Version: 0.1.0
Summary: A thin layer on top of FastAPI that adds some production readiness features.
Home-page: https://jmagnusson.github.io/prodapi/
License: MIT
Author: Jacob Magnusson
Author-email: m@jacobian.se
Requires-Python: >=3.6,<4.0
Classifier: Development Status :: 3 - Alpha
Classifier: Environment :: Web Environment
Classifier: Framework :: AsyncIO
Classifier: Intended Audience :: Developers
Classifier: Intended Audience :: Information Technology
Classifier: Intended Audience :: System Administrators
Classifier: License :: OSI Approved :: MIT License
Classifier: Operating System :: OS Independent
Classifier: Programming Language :: Python
Classifier: Programming Language :: Python :: 3
Classifier: Programming Language :: Python :: 3 :: Only
Classifier: Programming Language :: Python :: 3.6
Classifier: Programming Language :: Python :: 3.7
Classifier: Programming Language :: Python :: 3.8
Classifier: Programming Language :: Python :: 3.9
Classifier: Topic :: Internet
Classifier: Topic :: Internet :: WWW/HTTP
Classifier: Topic :: Software Development
Classifier: Topic :: Software Development :: Libraries
Classifier: Topic :: Software Development :: Libraries :: Python Modules
Classifier: Typing :: Typed
Requires-Dist: fastapi-security (>=0.3.1,<0.4.0)
Requires-Dist: importlib_metadata (>=3,<4); python_version < "3.8"
Requires-Dist: orjson (>=3,<4)
Project-URL: Documentation, https://jmagnusson.github.io/prodapi/
Project-URL: Repository, https://github.com/jmagnusson/prodapi
